odoo/addons/shopinvader_search_engine_update/README.rst
odoo/addons/shopinvader_search_engine_update/__init__.py
odoo/addons/shopinvader_search_engine_update/__manifest__.py
odoo/addons/shopinvader_search_engine_update/i18n/shopinvader_search_engine_update.pot
odoo/addons/shopinvader_search_engine_update/models/__init__.py
odoo/addons/shopinvader_search_engine_update/models/product_product.py
odoo/addons/shopinvader_search_engine_update/models/product_template.py
odoo/addons/shopinvader_search_engine_update/models/se_indexable_record.py
odoo/addons/shopinvader_search_engine_update/models/se_product_update_mixin.py
odoo/addons/shopinvader_search_engine_update/readme/CONTEXT.md
odoo/addons/shopinvader_search_engine_update/readme/CONTRIBUTORS.md
odoo/addons/shopinvader_search_engine_update/readme/DESCRIPTION.md
odoo/addons/shopinvader_search_engine_update/static/description/icon.png
odoo/addons/shopinvader_search_engine_update/static/description/index.html
odoo/addons/shopinvader_search_engine_update/tests/__init__.py
odoo/addons/shopinvader_search_engine_update/tests/common.py
odoo/addons/shopinvader_search_engine_update/tests/test_update.py
odoo_addon_shopinvader_search_engine_update-16.0.1.0.2.dist-info/METADATA
odoo_addon_shopinvader_search_engine_update-16.0.1.0.2.dist-info/WHEEL
odoo_addon_shopinvader_search_engine_update-16.0.1.0.2.dist-info/top_level.txt
odoo_addon_shopinvader_search_engine_update-16.0.1.0.2.dist-info/RECORD
